LICENSE
MANIFEST.in
README.md
setup.py
demo/__init__.py
demo/manage.py
demo/demo_unifi_portal/__init__.py
demo/demo_unifi_portal/settings.py
demo/demo_unifi_portal/unifi_secret.py
demo/demo_unifi_portal/unifi_settings.py
demo/demo_unifi_portal/urls.py
demo/demo_unifi_portal/wsgi.py
demo/tests/__init__.py
demo/tests/test_api_client.py
demo/tests/test_login.py
demo/unifi/__init__.py
demo/unifi/urls.py
demo/unifi/views.py
django_unifi_portal/__init__.py
django_unifi_portal/context_processor.py
django_unifi_portal/form_mixin.py
django_unifi_portal/forms.py
django_unifi_portal/models.py
django_unifi_portal/pipeline.py
django_unifi_portal/unifi_client.py
django_unifi_portal/urls.py
django_unifi_portal/views.py
django_unifi_portal.egg-info/PKG-INFO
django_unifi_portal.egg-info/SOURCES.txt
django_unifi_portal.egg-info/dependency_links.txt
django_unifi_portal.egg-info/not-zip-safe
django_unifi_portal.egg-info/requires.txt
django_unifi_portal.egg-info/top_level.txt
django_unifi_portal/migrations/0001_initial.py
django_unifi_portal/migrations/0002_auto_20170612_1252.py
django_unifi_portal/migrations/0003_auto_20170613_1258.py
django_unifi_portal/migrations/0004_auto_20170613_1638.py
django_unifi_portal/migrations/__init__.py
django_unifi_portal/static/css/font-awesome.css
django_unifi_portal/static/css/font-awesome.min.css
django_unifi_portal/static/fonts/FontAwesome.otf
django_unifi_portal/static/fonts/fontawesome-webfont.eot
django_unifi_portal/static/fonts/fontawesome-webfont.svg
django_unifi_portal/static/fonts/fontawesome-webfont.ttf
django_unifi_portal/static/fonts/fontawesome-webfont.woff
django_unifi_portal/static/fonts/fontawesome-webfont.woff2
django_unifi_portal/static/img/DjangoUniFi.png
django_unifi_portal/static/js/jquery-2.1.1.min.js
django_unifi_portal/templates/base.html
django_unifi_portal/templates/base_form.html
django_unifi_portal/templates/index.html
django_unifi_portal/templates/logged_out.html
django_unifi_portal/templates/login.html
django_unifi_portal/templates/registration.html